{
  "Barbarian": [
    {"name": "Rage", "level": 1, "description": "Enter a primal state granting damage resistance, bonus damage on Strength attacks, advantage on Strength checks/saves."},
    {"name": "Unarmored Defense", "level": 1, "description": "When not wearing armor, AC equals 10 plus Dexterity and Constitution modifiers."},
    {"name": "Weapon Mastery", "level": 1, "description": "Use mastery properties of two chosen melee weapons."},
    {"name": "Danger Sense", "level": 2, "description": "Gain advantage on Dexterity saving throws unless incapacitated."},
    {"name": "Reckless Attack", "level": 2, "description": "Attack with advantage on Strength rolls, but enemies gain advantage against you until your next turn."},
    {"name": "Barbarian Subclass", "level": 3, "description": "Choose a subclass specialization."},
    {"name": "Primal Knowledge", "level": 3, "description": "Gain an additional skill proficiency and can use Strength for certain skills while raging."},
    {"name": "Ability Score Improvement", "level": 4, "description": "Gain an ability score increase or feat. Received again at levels 8, 12, and 16."},
    {"name": "Extra Attack", "level": 5, "description": "Attack twice instead of once when taking the Attack action."},
    {"name": "Fast Movement", "level": 5, "description": "Speed increases by 10 feet while not wearing heavy armor."},
    {"name": "Feral Instinct", "level": 7, "description": "Gain advantage on initiative rolls."},
    {"name": "Instinctive Pounce", "level": 7, "description": "Move up to half your speed as part of the bonus action used to enter rage."},
    {"name": "Brutal Strike", "level": 9, "description": "When using Reckless Attack, forgo advantage to add 1d10 damage with special effects."},
    {"name": "Relentless Rage", "level": 11, "description": "When dropping to 0 HP while raging, make a Constitution save to restore HP."},
    {"name": "Improved Brutal Strike", "level": 13, "description": "Unlock additional Brutal Strike effects: Staggering Blow and Sundering Blow."},
    {"name": "Persistent Rage", "level": 15, "description": "Regain all rage uses when rolling initiative. Rage lasts 10 minutes."},
    {"name": "Improved Brutal Strike (Enhanced)", "level": 17, "description": "Brutal Strike extra damage increases to 2d10, apply two effects simultaneously."},
    {"name": "Indomitable Might", "level": 18, "description": "On Strength checks or saves, use your Strength score if higher than your roll."},
    {"name": "Epic Boon", "level": 19, "description": "Gain an Epic Boon feat or another qualifying feat."},
    {"name": "Primal Champion", "level": 20, "description": "Strength and Constitution scores increase by 4, to a maximum of 25."},
    {"name": "Frenzy", "level": 3, "description": "While using Reckless Attack during rage, deal extra damage on the first target hit."},
    {"name": "Mindless Rage", "level": 6, "description": "Gain immunity to charmed and frightened conditions while raging."},
    {"name": "Retaliation", "level": 10, "description": "When damaged by a creature within 5 feet, use reaction to make one melee attack."},
    {"name": "Intimidating Presence", "level": 14, "description": "Use bonus action to frighten creatures in a 30-foot radius."}
  ],
  "Bard": [
    {"name": "Bardic Inspiration", "level": 1, "description": "Inspire creatures within 60 feet as a bonus action, granting a Bardic Inspiration die to add to a failed d20 test."},
    {"name": "Spellcasting", "level": 1, "description": "Cast spells using Charisma. Know two cantrips from the Bard spell list."},
    {"name": "Expertise", "level": 2, "description": "Gain expertise in two skill proficiencies. Gain two more at level 9."},
    {"name": "Jack of All Trades", "level": 2, "description": "Add half your proficiency bonus to ability checks using skills you lack proficiency in."},
    {"name": "Bard Subclass", "level": 3, "description": "Choose a Bard subclass specialization."},
    {"name": "Ability Score Improvement", "level": 4, "description": "Gain an ability score increase or feat. Again at levels 8, 12, and 16."},
    {"name": "Font of Inspiration", "level": 5, "description": "Regain all Bardic Inspiration uses on short or long rest."},
    {"name": "Countercharm", "level": 7, "description": "When you or ally within 30 feet fails a save against charmed or frightened, use reaction to reroll with advantage."},
    {"name": "Magical Secrets", "level": 10, "description": "Choose prepared spells from Bard, Cleric, Druid, or Wizard spell lists."},
    {"name": "Superior Inspiration", "level": 18, "description": "When rolling initiative, regain Bardic Inspiration uses until you have two."},
    {"name": "Epic Boon", "level": 19, "description": "Gain an Epic Boon feat or another qualifying feat."},
    {"name": "Words of Creation", "level": 20, "description": "Always have Power Word Heal and Power Word Kill prepared."},
    {"name": "Bonus Proficiencies", "level": 3, "description": "College of Lore: Gain proficiency with three skills."},
    {"name": "Cutting Words", "level": 3, "description": "College of Lore: Expend Bardic Inspiration as reaction to subtract die from creature's roll."},
    {"name": "Magical Discoveries", "level": 6, "description": "College of Lore: Learn two spells from Cleric, Druid, or Wizard lists."},
    {"name": "Peerless Skill", "level": 14, "description": "College of Lore: When failing ability check or attack, expend Bardic Inspiration to add the roll."}
  ],
  "Cleric": [
    {"name": "Spellcasting", "level": 1, "description": "Cast spells through prayer and meditation using Wisdom. Know three cantrips and prepare spells based on available slots."},
    {"name": "Divine Order", "level": 1, "description": "Choose between Protector (martial weapons and heavy armor) or Thaumaturge (extra cantrip and bonus to Arcana/Religion checks)."},
    {"name": "Channel Divinity", "level": 2, "description": "Channel divine energy to fuel magical effects including Divine Spark and Turn Undead, usable twice before needing rest."},
    {"name": "Cleric Subclass", "level": 3, "description": "Select a specialization such as Life Domain that grants additional features at specific levels."},
    {"name": "Ability Score Improvement", "level": 4, "description": "Gain a feat or ability score increase, repeatable at levels 8, 12, and 16."},
    {"name": "Sear Undead", "level": 5, "description": "When using Turn Undead, undead that fail suffer additional Radiant damage equal to rolled dice based on Wisdom modifier."},
    {"name": "Blessed Strikes", "level": 7, "description": "Choose Divine Strike (1d8 extra damage once per turn) or Potent Spellcasting (add Wisdom to cantrip damage)."},
    {"name": "Divine Intervention", "level": 10, "description": "Cast any Cleric spell of level 5 or lower without using a spell slot, usable once per Long Rest."},
    {"name": "Improved Blessed Strikes", "level": 14, "description": "Divine Strike increases to 2d8 damage, or Potent Spellcasting grants temporary hit points equal to twice Wisdom modifier."},
    {"name": "Epic Boon", "level": 19, "description": "Gain an Epic Boon feat or another feat for which you qualify."},
    {"name": "Greater Divine Intervention", "level": 20, "description": "When using Divine Intervention, you may cast Wish, but cannot use the feature again until finishing 2d4 Long Rests."},
    {"name": "Disciple of Life", "level": 3, "description": "Life Domain: When healing spells restore hit points, add 2 plus the spell slot level in additional healing."},
    {"name": "Life Domain Spells", "level": 3, "description": "Life Domain: Automatically prepare specific healing and restoration spells without counting against preparation limit."},
    {"name": "Preserve Life", "level": 3, "description": "Life Domain: Expend Channel Divinity to restore hit points equal to five times Cleric level among bloodied creatures within 30 feet."},
    {"name": "Blessed Healer", "level": 6, "description": "Life Domain: Regain hit points equal to 2 plus spell slot level after casting healing spells on other creatures."},
    {"name": "Supreme Healing", "level": 17, "description": "Life Domain: Healing spells and Channel Divinity automatically roll the highest possible value for each die."}
  ],
  "Druid": [
    {"name": "Spellcasting", "level": 1, "description": "Cast spells using Wisdom as your spellcasting ability, with access to cantrips and prepared spells from the Druid spell list."},
    {"name": "Druidic", "level": 1, "description": "Know the secret language of Druids, always have Speak with Animals prepared, and can leave hidden messages in Druidic."},
    {"name": "Primal Order", "level": 1, "description": "Choose between Magician (extra cantrip and bonus to Arcana/Nature checks) or Warden (Martial weapons and Medium armor proficiency)."},
    {"name": "Wild Shape", "level": 2, "description": "Transform into Beast forms as a bonus action, gaining temporary hit points and using the creature's statistics while retaining your mind."},
    {"name": "Wild Companion", "level": 2, "description": "Cast Find Familiar by expending a spell slot or Wild Shape use, summoning a Fey familiar that disappears at long rest."},
    {"name": "Druid Subclass", "level": 3, "description": "Gain a specialization from a Druid subclass, gaining its features at appropriate levels."},
    {"name": "Ability Score Improvement", "level": 4, "description": "Gain the Ability Score Improvement feat or another qualifying feat. Repeats at levels 8, 12, and 16."},
    {"name": "Wild Resurgence", "level": 5, "description": "Regain a Wild Shape use by expending a spell slot, or convert a Wild Shape use into a level 1 spell slot once per long rest."},
    {"name": "Elemental Fury", "level": 7, "description": "Choose Potent Spellcasting to add Wisdom to cantrip damage, or Primal Strike to add 1d8 extra damage to weapon/beast attacks."},
    {"name": "Improved Elemental Fury", "level": 15, "description": "Potent Spellcasting range increases by 300 feet, or Primal Strike extra damage becomes 2d8."},
    {"name": "Beast Spells", "level": 18, "description": "While in Wild Shape form, you can cast spells except those with costly or consumable Material components."},
    {"name": "Epic Boon", "level": 19, "description": "Gain an Epic Boon feat or another qualifying feat of your choice."},
    {"name": "Archdruid", "level": 20, "description": "Regain one Wild Shape use when rolling Initiative if you have none, convert Wild Shape uses into spell slots, and age slowly."},
    {"name": "Circle of the Land Spells", "level": 3, "description": "Circle of the Land: Choose a land type and automatically prepare bonus spells associated with that terrain."},
    {"name": "Land's Aid", "level": 3, "description": "Circle of the Land: Expend a Wild Shape use to create a sphere where enemies take 2d6 necrotic damage and one ally regains 2d6 HP."},
    {"name": "Natural Recovery", "level": 6, "description": "Circle of the Land: Cast one Circle spell without a slot after long rest, and recover spell slots after short rests."},
    {"name": "Nature's Ward", "level": 10, "description": "Circle of the Land: Gain immunity to the Poisoned condition and resistance to damage matching your chosen land type."},
    {"name": "Nature's Sanctuary", "level": 14, "description": "Circle of the Land: Create spectral trees granting you and allies half cover and your Nature's Ward resistance for up to one minute."}
  ],
  "Fighter": [
    {"name": "Fighting Style", "level": 1, "description": "Choose a Fighting Style feat that grants martial bonuses. You may swap your choice whenever you gain a Fighter level."},
    {"name": "Second Wind", "level": 1, "description": "Use a Bonus Action to regain HP equal to 1d10 plus your Fighter level. You have 2 uses, regaining one per Short Rest."},
    {"name": "Weapon Mastery", "level": 1, "description": "Gain mastery properties for 3 Simple or Martial weapons of your choice, changeable after each Long Rest."},
    {"name": "Action Surge", "level": 2, "description": "Take one additional action on your turn (except Magic action). Recharges after a Short or Long Rest."},
    {"name": "Tactical Mind", "level": 2, "description": "When failing an ability check, expend a Second Wind use to add 1d10 to the check."},
    {"name": "Fighter Subclass", "level": 3, "description": "Choose a Fighter subclass specialization that grants additional features at specified levels."},
    {"name": "Ability Score Improvement", "level": 4, "description": "Gain an Ability Score Improvement feat or another feat. Repeats at levels 6, 8, 12, 14, and 16."},
    {"name": "Extra Attack", "level": 5, "description": "Attack twice instead of once when taking the Attack action on your turn."},
    {"name": "Tactical Shift", "level": 5, "description": "When using Second Wind, move up to half your Speed without provoking Opportunity Attacks."},
    {"name": "Indomitable", "level": 9, "description": "Reroll a failed saving throw with a bonus equal to your Fighter level. Additional uses at levels 13 and 17."},
    {"name": "Tactical Master", "level": 9, "description": "Replace a weapon's mastery property with Push, Sap, or Slow for individual attacks."},
    {"name": "Two Extra Attacks", "level": 11, "description": "Attack three times instead of once when taking the Attack action on your turn."},
    {"name": "Studied Attacks", "level": 13, "description": "Gain Advantage on your next attack against a creature you missed since your last turn."},
    {"name": "Epic Boon", "level": 19, "description": "Gain an Epic Boon feat or another feat of your choice for which you meet the requirements."},
    {"name": "Three Extra Attacks", "level": 20, "description": "Attack four times instead of once when taking the Attack action on your turn."},
    {"name": "Improved Critical", "level": 3, "description": "Champion: Weapon and Unarmed Strike attacks score Critical Hits on a roll of 19 or 20."},
    {"name": "Remarkable Athlete", "level": 3, "description": "Champion: Gain Advantage on Initiative rolls and Strength (Athletics) checks. Move half your Speed after Critical Hits."},
    {"name": "Additional Fighting Style", "level": 7, "description": "Champion: Gain a second Fighting Style feat of your choice."},
    {"name": "Heroic Warrior", "level": 10, "description": "Champion: Grant yourself Heroic Inspiration at the start of each combat turn if you lack it."},
    {"name": "Superior Critical", "level": 15, "description": "Champion: Weapon and Unarmed Strike attacks score Critical Hits on a roll of 18-20."},
    {"name": "Survivor", "level": 18, "description": "Champion: Advantage on Death Saves, treat 18-20 as 20. Regain HP at turn start if Bloodied."}
  ],
  "Monk": [
    {"name": "Martial Arts", "level": 1, "description": "Gain mastery of unarmed strikes and monk weapons with bonus unarmed strikes, a martial arts die, and Dexterity for attacks."},
    {"name": "Unarmored Defense", "level": 1, "description": "When unarmored, your AC equals 10 plus your Dexterity and Wisdom modifiers."},
    {"name": "Monk's Focus", "level": 2, "description": "Harness focus points to fuel Flurry of Blows, Patient Defense, and Step of the Wind."},
    {"name": "Unarmored Movement", "level": 2, "description": "Movement speed increases by 10 feet while unarmored, scaling up to 30 feet at higher levels."},
    {"name": "Uncanny Metabolism", "level": 2, "description": "When rolling initiative, regain all focus points and hit points equal to monk level plus a martial arts die roll."},
    {"name": "Deflect Attacks", "level": 3, "description": "Reduce incoming bludgeoning, piercing, or slashing damage by 1d10 plus Dexterity modifier and monk level, optionally redirecting damage."},
    {"name": "Monk Subclass", "level": 3, "description": "Choose a monastic tradition specialization, gaining subclass features at specified levels."},
    {"name": "Ability Score Improvement", "level": 4, "description": "Gain an ability score improvement feat or another feat you qualify for. Repeats at levels 8, 12, and 16."},
    {"name": "Slow Fall", "level": 4, "description": "Use a reaction to reduce fall damage by an amount equal to five times your monk level."},
    {"name": "Extra Attack", "level": 5, "description": "Attack twice instead of once when taking the Attack action on your turn."},
    {"name": "Stunning Strike", "level": 5, "description": "Expend a focus point when hitting to force a Constitution save, potentially stunning the target."},
    {"name": "Empowered Strikes", "level": 6, "description": "Your unarmed strikes can deal force damage instead of their normal damage type."},
    {"name": "Evasion", "level": 7, "description": "When making a Dexterity save for half damage, take no damage on success and half on failure."},
    {"name": "Acrobatic Movement", "level": 9, "description": "Move along vertical surfaces and across liquids without falling while unarmored."},
    {"name": "Heightened Focus", "level": 10, "description": "Flurry of Blows makes three strikes, Patient Defense grants temporary HP, and Step of the Wind moves willing creatures."},
    {"name": "Self-Restoration", "level": 10, "description": "Remove charmed, frightened, or poisoned conditions at turn's end; forgoing food and drink doesn't cause exhaustion."},
    {"name": "Deflect Energy", "level": 13, "description": "Deflect Attacks now works against any damage type, not just bludgeoning, piercing, or slashing."},
    {"name": "Disciplined Survivor", "level": 14, "description": "Gain proficiency in all saving throws; expend a focus point to reroll a failed save."},
    {"name": "Perfect Focus", "level": 15, "description": "When rolling initiative without Uncanny Metabolism, regain focus points up to 4 if you have 3 or fewer."},
    {"name": "Superior Defense", "level": 18, "description": "Expend 3 focus points to gain resistance to all damage except force for 1 minute."},
    {"name": "Epic Boon", "level": 19, "description": "Gain an Epic Boon feat or another feat you qualify for."},
    {"name": "Body and Mind", "level": 20, "description": "Increase Dexterity and Wisdom scores by 4 each, to a maximum of 25."},
    {"name": "Open Hand Technique", "level": 3, "description": "Warrior of the Open Hand: After hitting with Flurry of Blows, impose Addle, Push, or Topple effects on the target."},
    {"name": "Wholeness of Body", "level": 6, "description": "Warrior of the Open Hand: As a bonus action, roll your martial arts die to regain HP plus your Wisdom modifier."},
    {"name": "Fleet Step", "level": 11, "description": "Warrior of the Open Hand: After using a bonus action other than Step of the Wind, immediately use Step of the Wind."},
    {"name": "Quivering Palm", "level": 17, "description": "Warrior of the Open Hand: Expend 4 focus points on an unarmed strike to set vibrations that later deal 10d12 force damage."}
  ],
  "Paladin": [
    {"name": "Lay On Hands", "level": 1, "description": "Pool of healing power equal to 5 times Paladin level, usable as bonus action to restore HP or remove Poisoned condition."},
    {"name": "Spellcasting", "level": 1, "description": "Cast Paladin spells using Charisma, prepare spells from the Paladin spell list, and use Holy Symbol as focus."},
    {"name": "Weapon Mastery", "level": 1, "description": "Gain mastery properties for two weapon types of your choice, switchable after each Long Rest."},
    {"name": "Fighting Style", "level": 2, "description": "Choose a Fighting Style feat or Blessed Warrior to learn two Cleric cantrips with Charisma."},
    {"name": "Paladin's Smite", "level": 2, "description": "Always have Divine Smite prepared and can cast it once without expending a spell slot per Long Rest."},
    {"name": "Channel Divinity", "level": 3, "description": "Channel divine energy for magical effects like Divine Sense; gain two uses regaining on Short and Long Rest."},
    {"name": "Paladin Subclass", "level": 3, "description": "Choose a subclass specialization that grants additional features at specified levels."},
    {"name": "Ability Score Improvement", "level": 4, "description": "Gain an Ability Score Improvement feat or another feat. Repeats at levels 8, 12, and 16."},
    {"name": "Extra Attack", "level": 5, "description": "Attack twice instead of once when taking the Attack action on your turn."},
    {"name": "Faithful Steed", "level": 5, "description": "Always have Find Steed prepared and can cast it once without a spell slot per Long Rest."},
    {"name": "Aura of Protection", "level": 6, "description": "Emanate a 10-foot aura granting you and allies bonus to saving throws equal to your Charisma modifier."},
    {"name": "Abjure Foes", "level": 9, "description": "Expend Channel Divinity to frighten creatures equal to Charisma modifier within 60 feet."},
    {"name": "Aura of Courage", "level": 10, "description": "You and allies gain immunity to Frightened while in your Aura of Protection."},
    {"name": "Radiant Strikes", "level": 11, "description": "All melee weapon and unarmed strike attacks deal an extra 1d8 radiant damage."},
    {"name": "Restoring Touch", "level": 14, "description": "When using Lay On Hands, expend 5 HP per condition to remove Blinded, Charmed, Deafened, Frightened, Paralyzed, or Stunned."},
    {"name": "Aura Expansion", "level": 18, "description": "Your Aura of Protection expands from 10 feet to 30 feet."},
    {"name": "Epic Boon", "level": 19, "description": "Gain an Epic Boon feat or another feat of your choice for which you qualify."},
    {"name": "Oath of Devotion Spells", "level": 3, "description": "Oath of Devotion: Automatically prepare specific spells like Protection from Evil and Good and Shield of Faith."},
    {"name": "Sacred Weapon", "level": 3, "description": "Oath of Devotion: Expend Channel Divinity to add Charisma modifier to attack rolls with one weapon for 10 minutes."},
    {"name": "Aura of Devotion", "level": 7, "description": "Oath of Devotion: You and allies gain immunity to Charmed while in your Aura of Protection."},
    {"name": "Smite of Protection", "level": 15, "description": "Oath of Devotion: When casting Divine Smite, you and allies gain half cover in your aura until your next turn."},
    {"name": "Holy Nimbus", "level": 20, "description": "Oath of Devotion: Activate 10-minute aura granting advantage on saves against Fiends/Undead, radiant damage to enemies, and sunlight."}
  ],
  "Ranger": [
    {"name": "Spellcasting", "level": 1, "description": "Channel nature's magic to cast spells using Wisdom as your spellcasting ability."},
    {"name": "Favored Enemy", "level": 1, "description": "Always have Hunter's Mark prepared and can cast it twice per long rest without expending spell slots."},
    {"name": "Weapon Mastery", "level": 1, "description": "Gain mastery properties for two weapon types of your choice, changeable after each long rest."},
    {"name": "Deft Explorer", "level": 2, "description": "Gain expertise in one skill proficiency and learn two additional languages."},
    {"name": "Fighting Style", "level": 2, "description": "Choose a fighting style feat or learn two druid cantrips that count as ranger spells."},
    {"name": "Ranger Subclass", "level": 3, "description": "Select a subclass specialization that provides features at certain ranger levels."},
    {"name": "Ability Score Improvement", "level": 4, "description": "Gain the Ability Score Improvement feat or another qualifying feat. Repeats at levels 8, 12, and 16."},
    {"name": "Extra Attack", "level": 5, "description": "Attack twice when taking the Attack action on your turn."},
    {"name": "Roving", "level": 6, "description": "Gain 10 feet additional speed without heavy armor plus climb and swim speeds equal to your movement speed."},
    {"name": "Expertise", "level": 9, "description": "Gain expertise in two additional skill proficiencies."},
    {"name": "Tireless", "level": 10, "description": "Gain temporary hit points as a magic action and reduce exhaustion by 1 after each short rest."},
    {"name": "Relentless Hunter", "level": 13, "description": "Taking damage cannot break your concentration on Hunter's Mark."},
    {"name": "Nature's Veil", "level": 14, "description": "Use a bonus action to become invisible until the end of your next turn, usable Wisdom modifier times per long rest."},
    {"name": "Precise Hunter", "level": 17, "description": "Gain advantage on attack rolls against creatures marked by your Hunter's Mark."},
    {"name": "Feral Senses", "level": 18, "description": "Gain blindsight with a 30-foot range."},
    {"name": "Epic Boon", "level": 19, "description": "Gain an Epic Boon feat or another qualifying feat of your choice."},
    {"name": "Foe Slayer", "level": 20, "description": "Increase the damage die of your Hunter's Mark from d6 to d10."},
    {"name": "Hunter's Lore", "level": 3, "description": "Hunter: Reveal immunities, resistances, and vulnerabilities of creatures marked by your Hunter's Mark."},
    {"name": "Hunter's Prey", "level": 3, "description": "Hunter: Choose Colossus Slayer or Horde Breaker, switchable after short or long rests."},
    {"name": "Defensive Tactics", "level": 7, "description": "Hunter: Choose Escape the Horde or Multiattack Defense, switchable after short or long rests."},
    {"name": "Superior Hunter's Prey", "level": 11, "description": "Hunter: Once per turn, apply Hunter's Mark extra damage to another creature within 30 feet of your marked target."},
    {"name": "Superior Hunter's Defense", "level": 15, "description": "Hunter: Use a reaction to gain resistance to damage taken until the end of your current turn."}
  ],
  "Rogue": [
    {"name": "Expertise", "level": 1, "description": "Gain expertise in two skill proficiencies of your choice, and two more at level 6."},
    {"name": "Sneak Attack", "level": 1, "description": "Deal extra damage (1d6 to 10d6) once per turn with finesse or ranged weapons when you have advantage or an ally is near the target."},
    {"name": "Thieves' Cant", "level": 1, "description": "You know the secret Thieves' Cant language and one additional language of your choice."},
    {"name": "Weapon Mastery", "level": 1, "description": "Use the mastery properties of two weapon types you're proficient with, changeable after each long rest."},
    {"name": "Cunning Action", "level": 2, "description": "Take Dash, Disengage, or Hide as a bonus action on your turn."},
    {"name": "Rogue Subclass", "level": 3, "description": "Choose a subclass specialization that grants features at specific levels."},
    {"name": "Steady Aim", "level": 3, "description": "Gain advantage on your next attack as a bonus action, but your speed becomes 0 until turn end."},
    {"name": "Ability Score Improvement", "level": 4, "description": "Gain a feat or ability score improvement at levels 4, 8, 10, 12, and 16."},
    {"name": "Cunning Strike", "level": 5, "description": "When dealing sneak attack damage, spend damage dice to add effects like Poison, Trip, or Withdraw."},
    {"name": "Uncanny Dodge", "level": 5, "description": "Use a reaction to halve damage from an attack you can see."},
    {"name": "Evasion", "level": 7, "description": "Take no damage on successful Dexterity saves against effects that normally deal half damage."},
    {"name": "Reliable Talent", "level": 7, "description": "Treat d20 rolls of 9 or lower as 10 for ability checks using your skill or tool proficiencies."},
    {"name": "Improved Cunning Strike", "level": 11, "description": "Apply up to two cunning strike effects when dealing sneak attack damage."},
    {"name": "Devious Strikes", "level": 14, "description": "Unlock three new cunning strike options: Daze, Knock Out, and Obscure with escalating die costs."},
    {"name": "Slippery Mind", "level": 15, "description": "Gain proficiency in Wisdom and Charisma saving throws."},
    {"name": "Elusive", "level": 18, "description": "Attack rolls against you can't have advantage unless you're incapacitated."},
    {"name": "Epic Boon", "level": 19, "description": "Gain an epic boon feat or another feat you qualify for."},
    {"name": "Stroke of Luck", "level": 20, "description": "Convert one failed d20 test into a natural 20 per short or long rest."},
    {"name": "Fast Hands", "level": 3, "description": "Thief: Use a bonus action to make sleight of hand checks or utilize/activate magic items."},
    {"name": "Second-Story Work", "level": 3, "description": "Thief: Gain climb speed equal to your movement speed and determine jumps using Dexterity."},
    {"name": "Supreme Sneak", "level": 9, "description": "Thief: Add Stealth Attack cunning strike option to remain hidden after attacking if behind cover."},
    {"name": "Use Magic Device", "level": 13, "description": "Thief: Attune to four items, reroll magic item charges on 6, and cast spell scrolls using Intelligence."},
    {"name": "Thief's Reflexes", "level": 17, "description": "Thief: Take two turns in the first round of combat at normal initiative and initiative minus 10."}
  ],
  "Sorcerer": [
    {"name": "Spellcasting", "level": 1, "description": "Cast spells using Charisma as your spellcasting ability. Know 4 cantrips and prepare spells based on your Sorcerer level."},
    {"name": "Innate Sorcery", "level": 1, "description": "As a bonus action, gain +1 spell save DC and advantage on spell attack rolls for 1 minute. Two uses per long rest."},
    {"name": "Font of Magic", "level": 2, "description": "Gain Sorcery Points equal to your Sorcerer level that can be converted from or into spell slots."},
    {"name": "Metamagic", "level": 2, "description": "Choose two Metamagic options to modify spells by spending Sorcery Points. Gain more options at levels 10 and 17."},
    {"name": "Sorcerer Subclass", "level": 3, "description": "Select a specialization like Draconic Sorcery that grants unique features at specific levels."},
    {"name": "Ability Score Improvement", "level": 4, "description": "Gain an Ability Score Improvement feat or another feat. Repeats at levels 8, 12, and 16."},
    {"name": "Sorcerous Restoration", "level": 5, "description": "During a short rest, regain Sorcery Points up to half your Sorcerer level. Usable once per long rest."},
    {"name": "Sorcery Incarnate", "level": 7, "description": "Spend 2 Sorcery Points to activate Innate Sorcery if no uses remain. While active, apply two Metamagic options per spell."},
    {"name": "Epic Boon", "level": 19, "description": "Gain an Epic Boon feat or another feat of your choice for which you qualify."},
    {"name": "Arcane Apotheosis", "level": 20, "description": "While Innate Sorcery is active, use one Metamagic option per turn without spending Sorcery Points."},
    {"name": "Draconic Resilience", "level": 3, "description": "Draconic Sorcery: Increase max HP by 3 plus 1 per level. Gain dragon scales setting AC to 10 + Dexterity + Charisma when unarmored."},
    {"name": "Draconic Spells", "level": 3, "description": "Draconic Sorcery: Always have certain spells prepared based on Sorcerer level, including Chromatic Orb and Dragon's Breath."},
    {"name": "Elemental Affinity", "level": 6, "description": "Draconic Sorcery: Gain resistance to a dragon-associated damage type and add Charisma modifier to one damage roll of matching spells."},
    {"name": "Dragon Wings", "level": 14, "description": "Draconic Sorcery: Manifest draconic wings as a bonus action for 1 hour granting 60-foot fly speed."},
    {"name": "Dragon Companion", "level": 18, "description": "Draconic Sorcery: Cast Summon Dragon without a material component once per long rest, optionally without concentration for 1 minute."}
  ],
  "Warlock": [
    {"name": "Eldritch Invocations", "level": 1, "description": "Gain invocations providing forbidden knowledge that grants magical abilities, replaceable when leveling up."},
    {"name": "Pact Magic", "level": 1, "description": "Cast spells using Charisma through a pact with a mysterious entity. Spell slots refresh on short or long rests."},
    {"name": "Magical Cunning", "level": 2, "description": "Perform a 1-minute ritual to regain expended spell slots up to half your maximum, usable once per long rest."},
    {"name": "Warlock Subclass", "level": 3, "description": "Choose a subclass specialization granting additional features at certain levels."},
    {"name": "Ability Score Improvement", "level": 4, "description": "Gain an Ability Score Improvement feat or another feat. Repeats at levels 8, 12, and 16."},
    {"name": "Contact Patron", "level": 9, "description": "Always have Contact Other Plane prepared; cast it without a slot and automatically succeed on its save, once per long rest."},
    {"name": "Mystic Arcanum", "level": 11, "description": "Gain access to level 6-9 spells that can be cast once per long rest without expending spell slots."},
    {"name": "Epic Boon", "level": 19, "description": "Gain an Epic Boon feat or another feat of your choice for which you qualify."},
    {"name": "Eldritch Master", "level": 20, "description": "When using Magical Cunning, regain all expended Pact Magic spell slots instead of just half."},
    {"name": "Dark One's Blessing", "level": 3, "description": "Fiend Patron: Gain temporary HP equal to Charisma modifier plus Warlock level when you or an ally reduces an enemy to 0 HP nearby."},
    {"name": "Fiend Spells", "level": 3, "description": "Fiend Patron: Always have specific spells prepared based on your Warlock level."},
    {"name": "Dark One's Own Luck", "level": 6, "description": "Fiend Patron: Add 1d10 to ability checks or saving throws, usable Charisma modifier times per long rest."},
    {"name": "Fiendish Resilience", "level": 10, "description": "Fiend Patron: Choose a damage type each rest to gain resistance to until you choose a different one."},
    {"name": "Hurl Through Hell", "level": 14, "description": "Fiend Patron: When hitting with an attack, force target through a nightmare landscape dealing psychic damage and incapacitating it."}
  ],
  "Wizard": [
    {"name": "Spellcasting", "level": 1, "description": "Cast Wizard spells using Intelligence as your spellcasting ability, with cantrips, a spellbook, and prepared spells."},
    {"name": "Ritual Adept", "level": 1, "description": "Cast any Ritual-tagged spell from your spellbook without preparing it, reading from the book during casting."},
    {"name": "Arcane Recovery", "level": 1, "description": "During a Short Rest, recover spell slots with combined level up to half your Wizard level, no slot exceeding level 5."},
    {"name": "Scholar", "level": 2, "description": "Gain Expertise in one skill from Arcana, History, Investigation, Medicine, Nature, or Religion."},
    {"name": "Wizard Subclass", "level": 3, "description": "Choose a specialization granting features at certain Wizard levels throughout your career."},
    {"name": "Ability Score Improvement", "level": 4, "description": "Gain a feat or ability score increase. Repeats at levels 8, 12, and 16."},
    {"name": "Memorize Spell", "level": 5, "description": "After a Short Rest, swap one prepared spell for another from your spellbook of appropriate level."},
    {"name": "Spell Mastery", "level": 18, "description": "Select one level 1 and one level 2 spell to cast at will without slots."},
    {"name": "Epic Boon", "level": 19, "description": "Gain an Epic Boon feat or another feat of your choice for which you qualify."},
    {"name": "Signature Spells", "level": 20, "description": "Choose two level 3 spells to cast once each at level 3 without slots per Short or Long Rest."},
    {"name": "Evocation Savant", "level": 3, "description": "Evoker: Add two Evocation spells to your spellbook free, plus one new Evocation spell when gaining spell slot access."},
    {"name": "Potent Cantrip", "level": 3, "description": "Evoker: Cantrips deal half damage on missed attacks or failed saves, even when damage is normally negated."},
    {"name": "Sculpt Spells", "level": 6, "description": "Evoker: Designate creatures equal to 1 plus spell level to automatically succeed on saves and take no damage from your Evocation spells."},
    {"name": "Empowered Evocation", "level": 10, "description": "Evoker: Add your Intelligence modifier to one damage roll when casting an Evocation school spell."},
    {"name": "Overchannel", "level": 14, "description": "Evoker: Deal maximum damage with a level 1-5 Wizard spell; repeat uses before a Long Rest cause increasing Necrotic damage to yourself."}
  ]
}
